weheartpy/__init__.py
weheartpy/api.py
weheartpy/handler.py
weheartpy/models.py
weheartpy/weheartpy.py
weheartpy-0.2.4.dist-info/LICENSE
weheartpy-0.2.4.dist-info/METADATA
weheartpy-0.2.4.dist-info/WHEEL
weheartpy-0.2.4.dist-info/top_level.txt
weheartpy-0.2.4.dist-info/RECORD
