Metadata-Version: 2.1
Name: weheartpy
Version: 0.2.4
Summary: A comprehensive, realiable API client for weheartit.
Home-page: https://github.com/aswinnnn/weheartpy
Author: aswinnnn
Author-email: Aswin S <aswinsnair028@gmail.com>
License: MIT License        
Project-URL: Homepage, https://github.com/aswinnnn/weheartpy
Project-URL: Bug Tracker, https://github.com/aswinnnn/weheartpy/issues
Classifier: Programming Language :: Python :: 3
Classifier: License :: OSI Approved :: MIT License
Classifier: Operating System :: OS Independent
Requires-Python: >=3.10
License-File: LICENSE
Requires-Dist: beautifulsoup4
Requires-Dist: requests
Requires-Dist: lxml
Requires-Dist: user-agent
